<vcard><fn><text>0day.best</text></fn><kind><text>application</text></kind><url><uri>http://www.0day.best/</uri></url><registration xmlns='urn:xmpp:vcard:registration:1'><uri>xmpp:0day.best</uri></registration><bday><date>2020</date></bday><adr><country>RU</country></adr><ca xmlns='urn:xmpp:vcard:ca:0'><name>StartSSL</name><uri>http://www.startssl.com/</uri></ca><name xmlns='jabber:iq:version'>ejabberd</name><impp><uri>xmpp:xss@0day.best</uri></impp><geo><uri>geo:55.7644,37.6366</uri></geo><lang><parameters><pref>1</pref></parameters><language-tag>ru</language-tag></lang><email><text>hostmaster@0day.best</text></email></vcard>